Code/__init__.py
UTSGLDM1-0.0.0.dist-info/LICENSE.txt
UTSGLDM1-0.0.0.dist-info/METADATA
UTSGLDM1-0.0.0.dist-info/WHEEL
UTSGLDM1-0.0.0.dist-info/top_level.txt
UTSGLDM1-0.0.0.dist-info/RECORD
